wmicprocsdict/README.MD
wmicprocsdict/__init__.py
wmicprocsdict/requirements.txt
wmicprocsdict/thirdparty.json
wmicprocsdict-0.10.dist-info/LICENSE.rst
wmicprocsdict-0.10.dist-info/METADATA
wmicprocsdict-0.10.dist-info/WHEEL
wmicprocsdict-0.10.dist-info/top_level.txt
wmicprocsdict-0.10.dist-info/RECORD
