Metadata-Version: 2.1
Name: wmicprocsdict
Version: 0.10
Summary: Converts the output of a powershell (Get-...)/wmic command to a dict
Home-page: https://github.com/hansalemaos/wmicprocsdict
Author: Johannes Fischer
Author-email: aulasparticularesdealemaosp@gmail.com
License: MIT
Keywords: process,data
Classifier: Development Status :: 4 - Beta
Classifier: Programming Language :: Python :: 3 :: Only
Classifier: Programming Language :: Python :: 3.10
Classifier: Topic :: Software Development :: Libraries :: Python Modules
Classifier: Topic :: Utilities
License-File: LICENSE.rst
